LICENSE
MANIFEST.in
README.rst
setup.cfg
setup.py
api/__init__.py
api/admin.py
api/apps.py
api/models.py
api/tests.py
api/urls.py
api/views.py
api/migrations/0001_initial.py
api/migrations/__init__.py
developer/__init__.py
developer/asgi.py
developer/settings.py
developer/urls.py
developer/wsgi.py
django_lebelo.egg-info/PKG-INFO
django_lebelo.egg-info/SOURCES.txt
django_lebelo.egg-info/dependency_links.txt
django_lebelo.egg-info/top_level.txt