Metadata-Version: 2.1
Name: django-lebelo
Version: 0.0.1
Summary: lebelo.
Home-page: https://lebelo.co.ls/
Author: Your Name
Author-email: tebohonyenye1@gmail.com
License: BSD-3-Clause  # Example license
Classifier: Environment :: Web Environment
Classifier: Framework :: Django
Classifier: Intended Audience :: Developers
Classifier: License :: OSI Approved :: BSD License
Classifier: Operating System :: OS Independent
Classifier: Programming Language :: Python
Classifier: Programming Language :: Python :: 3
Classifier: Programming Language :: Python :: 3 :: Only
Classifier: Programming Language :: Python :: 3.10
Classifier: Topic :: Internet :: WWW/HTTP
Classifier: Topic :: Internet :: WWW/HTTP :: Dynamic Content
License-File: LICENSE
